odoo/addons/document_url_google_drive/README.rst
odoo/addons/document_url_google_drive/__init__.py
odoo/addons/document_url_google_drive/__manifest__.py
odoo/addons/document_url_google_drive/i18n/document_url_google_drive.pot
odoo/addons/document_url_google_drive/i18n/it.po
odoo/addons/document_url_google_drive/i18n/pt.po
odoo/addons/document_url_google_drive/models/__init__.py
odoo/addons/document_url_google_drive/models/res_config_settings.py
odoo/addons/document_url_google_drive/models/res_users.py
odoo/addons/document_url_google_drive/readme/CONFIGURE.md
odoo/addons/document_url_google_drive/readme/CONTRIBUTORS.md
odoo/addons/document_url_google_drive/readme/DESCRIPTION.md
odoo/addons/document_url_google_drive/readme/USAGE.md
odoo/addons/document_url_google_drive/readme/newsfragments/.gitkeep
odoo/addons/document_url_google_drive/static/description/banner.png
odoo/addons/document_url_google_drive/static/description/icon.png
odoo/addons/document_url_google_drive/static/description/icon.svg
odoo/addons/document_url_google_drive/static/description/index.html
odoo/addons/document_url_google_drive/static/img/gdrive_link.png
odoo/addons/document_url_google_drive/static/img/google_api_settings.png
odoo/addons/document_url_google_drive/static/src/img/logo-google-drive.png
odoo/addons/document_url_google_drive/static/src/js/attachment_google_picker.esm.js
odoo/addons/document_url_google_drive/static/src/xml/attachment_google_picker.xml
odoo/addons/document_url_google_drive/static/src/xml/google_picker_url.xml
odoo/addons/document_url_google_drive/tests/__init__.py
odoo/addons/document_url_google_drive/tests/test_document_url.py
odoo/addons/document_url_google_drive/views/res_config_settings_view.xml
odoo/addons/document_url_google_drive/views/res_users_view.xml
odoo/addons/document_url_google_drive/wizard/__init__.py
odoo/addons/document_url_google_drive/wizard/document_url.py
odoo_addon_document_url_google_drive-16.0.1.0.1.4.dist-info/METADATA
odoo_addon_document_url_google_drive-16.0.1.0.1.4.dist-info/WHEEL
odoo_addon_document_url_google_drive-16.0.1.0.1.4.dist-info/top_level.txt
odoo_addon_document_url_google_drive-16.0.1.0.1.4.dist-info/RECORD
